accessible_space/__init__.py
accessible_space/__main__.py
accessible_space/core.py
accessible_space/interface.py
accessible_space/motion_models.py
accessible_space/utility.py
accessible_space/apps/__init__.py
accessible_space/apps/qualitative_profiling.py
accessible_space/apps/readme.py
accessible_space/apps/validation.py
accessible_space/tests/__init__.py
accessible_space/tests/conftest.py
accessible_space/tests/resources.py
accessible_space/tests/test_dashboards.py
accessible_space/tests/test_model.py
accessible_space/tests/test_real_world_data.py
accessible_space-2.0.13.dist-info/licenses/LICENSE
accessible_space-2.0.13.dist-info/METADATA
accessible_space-2.0.13.dist-info/WHEEL
accessible_space-2.0.13.dist-info/top_level.txt
accessible_space-2.0.13.dist-info/RECORD
