Metadata-Version: 2.4
Name: accessible_space
Version: 2.0.13
Summary: Implementation of the Dangerous Accessible Space (DAS) passing model for football analytics.
Author-email: Jonas Bischofberger <jonas.bischofberger@univie.ac.at>
License: MIT License
Project-URL: Repository, https://github.com/jonas-bischofberger/accessible-space
Classifier: Programming Language :: Python
Classifier: Programming Language :: Python :: 3
Classifier: Programming Language :: Python :: 3.7
Classifier: Programming Language :: Python :: 3.8
Classifier: Programming Language :: Python :: 3.9
Classifier: Programming Language :: Python :: 3.10
Classifier: Programming Language :: Python :: 3.11
Classifier: Programming Language :: Python :: 3.12
Classifier: Programming Language :: Python :: 3.13
Requires-Python: >=3.7
License-File: LICENSE
Requires-Dist: matplotlib
Requires-Dist: numpy
Requires-Dist: pandas
Requires-Dist: scipy
Requires-Dist: tqdm
Provides-Extra: full
Requires-Dist: scikit-learn; extra == "full"
Requires-Dist: kloppy>=3.15.0; extra == "full"
Requires-Dist: xmltodict; extra == "full"
Requires-Dist: streamlit; extra == "full"
Requires-Dist: wfork-streamlit-profiler; extra == "full"
Requires-Dist: brokenaxes; extra == "full"
Requires-Dist: netcal; extra == "full"
Requires-Dist: mplsoccer; extra == "full"
Requires-Dist: databallpy; extra == "full"
Provides-Extra: dev
Requires-Dist: scikit-learn; extra == "dev"
Requires-Dist: kloppy>=3.15.0; extra == "dev"
Requires-Dist: xmltodict; extra == "dev"
Requires-Dist: streamlit; extra == "dev"
Requires-Dist: wfork-streamlit-profiler; extra == "dev"
Requires-Dist: brokenaxes; extra == "dev"
Requires-Dist: netcal; extra == "dev"
Requires-Dist: mplsoccer; extra == "dev"
Requires-Dist: databallpy; extra == "dev"
Requires-Dist: pytest; extra == "dev"
Requires-Dist: pytest-cov; extra == "dev"
Requires-Dist: build; extra == "dev"
Requires-Dist: twine; extra == "dev"
Requires-Dist: setuptools; extra == "dev"
Requires-Dist: tox; extra == "dev"
Requires-Dist: requests; extra == "dev"
Requires-Dist: packaging; extra == "dev"
Dynamic: license-file
